setlist_fm_client/__init__.py
setlist_fm_client/api.py
setlist_fm_client/async_api.py
setlist_fm_client/core.py
setlist_fm_client/enums.py
setlist_fm_client/models.py
setlist_fm_client/py.typed
setlist_fm_client-0.4.0.dist-info/LICENSE
setlist_fm_client-0.4.0.dist-info/WHEEL
setlist_fm_client-0.4.0.dist-info/METADATA
setlist_fm_client-0.4.0.dist-info/RECORD
