Metadata-Version: 2.1
Name: setlist-fm-client
Version: 0.4.0
Summary: a python client for the setlist.fm api
License: MIT
Author: Zach Schumacher
Author-email: zschu15@gmail.com
Requires-Python: >=3.7,<3.11
Classifier: Development Status :: 5 - Production/Stable
Classifier: Environment :: Console
Classifier: Environment :: MacOS X
Classifier: License :: OSI Approved :: MIT License
Classifier: Operating System :: POSIX :: Linux
Classifier: Operating System :: Unix
Classifier: Programming Language :: Python
Classifier: Programming Language :: Python :: 3
Classifier: Programming Language :: Python :: 3 :: Only
Classifier: Programming Language :: Python :: 3.10
Classifier: Programming Language :: Python :: 3.7
Classifier: Programming Language :: Python :: 3.8
Classifier: Programming Language :: Python :: 3.9
Classifier: Topic :: Software Development :: Libraries :: Python Modules
Requires-Dist: httpx (>=0.23.0,<0.24.0)
Requires-Dist: pydantic (>=1.9.1,<2.0.0)
Requires-Dist: pyhumps (>=3.7.1,<4.0.0)
